pyjar/__init__.py
pyjar/py.typed
pyjar-0.1.1.dist-info/LICENSE
pyjar-0.1.1.dist-info/METADATA
pyjar-0.1.1.dist-info/WHEEL
pyjar-0.1.1.dist-info/RECORD
