Metadata-Version: 2.1
Name: pyjar
Version: 0.1.1
Summary: Move Python things to other modules, mostly for backward-compatibility
License: Unlicense
Author: Peter Gaultney
Author-email: petergaultney@gmail.com
Requires-Python: >=3.7,<4.0
Classifier: License :: Other/Proprietary License
Classifier: Programming Language :: Python :: 3
Classifier: Programming Language :: Python :: 3.7
Classifier: Programming Language :: Python :: 3.8
Classifier: Programming Language :: Python :: 3.9
Classifier: Programming Language :: Python :: 3.10
Classifier: Programming Language :: Python :: 3.11
